LICENSE
MANIFEST.in
README.md
setup.py
quin/__init__.py
quin/core.py
quin/rua.py
quin.egg-info/PKG-INFO
quin.egg-info/SOURCES.txt
quin.egg-info/dependency_links.txt
quin.egg-info/entry_points.txt
quin.egg-info/top_level.txt
quin/static/quin.txt