Metadata-Version: 1.1
Name: quin
Version: 1.0.6
Summary: rua！真实终端大秦话
Home-page: https://github.com/journey-ad/quin
Author: journey.ad
Author-email: journey.adc@gmail.com
License: MIT
Platform: UNKNOWN
Classifier: Development Status :: 5 - Production/Stable
Classifier: Environment :: Console
Classifier: Operating System :: Unix
Classifier: Programming Language :: Python :: 3
Classifier: Programming Language :: Python :: 2
